go_retry/__init__.py
go_retry/api.py
go_retry/compat.py
retry/__init__.py
retry/api.py
retry/compat.py
go_retry-1.0.1.dist-info/AUTHORS
go_retry-1.0.1.dist-info/LICENSE
go_retry-1.0.1.dist-info/METADATA
go_retry-1.0.1.dist-info/WHEEL
go_retry-1.0.1.dist-info/top_level.txt
go_retry-1.0.1.dist-info/RECORD
