Metadata-Version: 2.1
Name: go-retry
Version: 1.0.1
Summary: Easy to use retry decorator, with fixes and updates.
Home-page: https://github.com/samc0de/retry
Author: (samc0de) Sameer Mahabole
Author-email: sssam.sam@gmail.com
License: UNKNOWN
Platform: UNKNOWN
Classifier: Programming Language :: Python :: 3
Requires-Python: >=3.7
License-File: LICENSE
License-File: AUTHORS
